{"textures":{"0":"modelengine:entity/deer"},"elements":[{"from":[6.89837,5.26111,6.8516297],"to":[8.2052,8.22326,8.6811905],"faces":{"east":{"uv":[16.0,3.5,15.25,5.0],"tintindex":0,"rotation":0,"texture":"#0"},"south":{"uv":[16.0,3.5,15.25,5.0],"tintindex":0,"rotation":0,"texture":"#0"},"north":{"uv":[16.0,3.5,15.25,5.0],"tintindex":0,"rotation":0,"texture":"#0"},"west":{"uv":[16.0,3.5,15.25,5.0],"tintindex":0,"rotation":0,"texture":"#0"},"up":{"uv":[16.0,3.5,15.25,5.0],"tintindex":0,"rotation":0,"texture":"#0"},"down":{"uv":[16.0,3.5,15.25,5.0],"tintindex":0,"rotation":0,"texture":"#0"}},"rotation":{"origin":[9.19602,8.68764,9.1026],"angle":-22.5,"axis":"x"}},{"from":[6.8112497,6.72971,7.76707],"to":[8.11808,8.73351,10.11936],"faces":{"east":{"uv":[8.75,3.5,7.75,4.5],"tintindex":0,"rotation":0,"texture":"#0"},"south":{"uv":[8.75,3.5,7.75,4.5],"tintindex":0,"rotation":0,"texture":"#0"},"north":{"uv":[8.75,3.5,7.75,4.5],"tintindex":0,"rotation":0,"texture":"#0"},"west":{"uv":[8.75,3.5,7.75,4.5],"tintindex":0,"rotation":0,"texture":"#0"},"up":{"uv":[8.75,3.5,7.75,4.5],"tintindex":0,"rotation":0,"texture":"#0"},"down":{"uv":[8.75,3.5,7.75,4.5],"tintindex":0,"rotation":0,"texture":"#0"}},"rotation":{"origin":[9.19602,8.68764,9.1026],"angle":22.5,"axis":"x"}}],"display":{"gui":{"rotation":[30,225,0]}}}