{"textures":{"0":"modelengine:entity/deer"},"elements":[{"from":[7.77452,4.52228,6.84136],"to":[9.08135,7.4844303,8.67092],"faces":{"east":{"uv":[16.0,3.5,15.25,5.0],"tintindex":0,"rotation":0,"texture":"#0"},"south":{"uv":[16.0,3.5,15.25,5.0],"tintindex":0,"rotation":0,"texture":"#0"},"north":{"uv":[16.0,3.5,15.25,5.0],"tintindex":0,"rotation":0,"texture":"#0"},"west":{"uv":[16.0,3.5,15.25,5.0],"tintindex":0,"rotation":0,"texture":"#0"},"up":{"uv":[16.0,3.5,15.25,5.0],"tintindex":0,"rotation":0,"texture":"#0"},"down":{"uv":[16.0,3.5,15.25,5.0],"tintindex":0,"rotation":0,"texture":"#0"}},"rotation":{"origin":[6.93578,7.9488106,9.09233],"angle":-22.5,"axis":"x"}},{"from":[7.86164,5.9908805,7.7568],"to":[9.16848,7.9946804,10.10909],"faces":{"east":{"uv":[8.75,3.5,7.75,4.5],"tintindex":0,"rotation":0,"texture":"#0"},"south":{"uv":[8.75,3.5,7.75,4.5],"tintindex":0,"rotation":0,"texture":"#0"},"north":{"uv":[8.75,3.5,7.75,4.5],"tintindex":0,"rotation":0,"texture":"#0"},"west":{"uv":[8.75,3.5,7.75,4.5],"tintindex":0,"rotation":0,"texture":"#0"},"up":{"uv":[8.75,3.5,7.75,4.5],"tintindex":0,"rotation":0,"texture":"#0"},"down":{"uv":[8.75,3.5,7.75,4.5],"tintindex":0,"rotation":0,"texture":"#0"}},"rotation":{"origin":[6.93578,7.9488106,9.09233],"angle":22.5,"axis":"x"}}],"display":{"gui":{"rotation":[30,225,0]}}}